vtex/__init__.py
vtex/api/__init__.py
vtex/api/base.py
vtex/api/catalog.py
vtex/api/logistics.py
vtex/api/orders.py
vtex/exceptions.py
vtex/py.typed.py
vtex/response.py
vtex/vtex.py
vtexpy-0.0.0.dist-info/LICENSE
vtexpy-0.0.0.dist-info/METADATA
vtexpy-0.0.0.dist-info/WHEEL
vtexpy-0.0.0.dist-info/RECORD
